facebook/__init__.py
facebook/base.py
facebook/user.py
facebook_api-0.1.10.dist-info/DESCRIPTION.rst
facebook_api-0.1.10.dist-info/METADATA
facebook_api-0.1.10.dist-info/RECORD
facebook_api-0.1.10.dist-info/WHEEL
facebook_api-0.1.10.dist-info/metadata.json
facebook_api-0.1.10.dist-info/top_level.txt
